{
  "project_info": {
    "project_number": "506583836414",
    "project_id": "diabuddy-production",
    "storage_bucket": "diabuddy-production.appspot.com"
  },
  "client": [
    {
      "client_info": {
        "mobilesdk_app_id": "1:506583836414:android:ab0aa3844f50dcc65867af",
        "android_client_info": {
          "package_name": "com.example.diabuddy"
        }
      },
      "oauth_client": [],
      "api_key": [
        {
          "current_key": "AIzaSyCmBbo-v0KvHk9tUNwWkVI3uvd-Iceykis"
        }
      ],
      "services": {
        "appinvite_service": {
          "other_platform_oauth_client": []
        }
      }
    }
  ],
  "configuration_version": "1"
}